rocketcea-1.2.2.dist-info/METADATA
rocketcea-1.2.2.dist-info/WHEEL
rocketcea/py_cea.cp310-win_amd64.pyd
rocketcea/py_cea.cp310-win_amd64.dll.a
rocketcea/__init__.py
rocketcea/_version.py
rocketcea/blends.py
rocketcea/cea_obj_w_units.py
rocketcea/cea_obj.py
rocketcea/clean_init.py
rocketcea/excel_const.py
rocketcea/find_mingw_lib.py
rocketcea/Goal.py
rocketcea/input_cards.py
rocketcea/Isp.py
rocketcea/separated_Cf.py
rocketcea/short_win_path.py
rocketcea/show_html_help.py
rocketcea/units.py
rocketcea/xlChart.py
rocketcea/xlChFormula.py
rocketcea/f.inp
rocketcea/f.out
rocketcea/thermo.inp
rocketcea/thermo.lib
rocketcea/thermo.out
rocketcea/temp.dat
rocketcea/trans.inp
rocketcea/trans.lib
rocketcea/trans.out
rocketcea/py_cea.f
rocketcea/py_cea.inc
rocketcea/biprop_utils/__init__.py
rocketcea/biprop_utils/back_terp.py
rocketcea/biprop_utils/calc_plot_range.py
rocketcea/biprop_utils/contour_supt.py
rocketcea/biprop_utils/density_at_mr.py
rocketcea/biprop_utils/goldSearch.py
rocketcea/biprop_utils/InterpProp_scipy.py
rocketcea/biprop_utils/mr_peak_at_eps_pc.py
rocketcea/biprop_utils/mr_t_limits.py
rocketcea/biprop_utils/rho_isp_plot_obj.py
rocketcea/biprop_utils/run_cea_w_error_corr.py
rocketcea/biprop_utils/veh_stage_obj.py
rocketcea/tests/__init__.py
rocketcea/tests/test_biprop_utils.py
rocketcea/tests/test_blend_defs.py
rocketcea/tests/test_cea_obj.py
rocketcea/tests/test_fac_CR.py
rocketcea/tests/test_misc.py
rocketcea/tests/test_transp_units.py
rocketcea/examples/adjust_ch4_t.py
rocketcea/examples/ambient_Cf.py
rocketcea/examples/amm_dissociation.py
rocketcea/examples/basic_chart.py
rocketcea/examples/cea_compare2.py
rocketcea/examples/cea_compare3.py
rocketcea/examples/cea_compare_mono.py
rocketcea/examples/cea_compareRhoIsp.py
rocketcea/examples/cea_cstar_plot.py
rocketcea/examples/cea_plot.py
rocketcea/examples/chk_cea_addpropellant.py
rocketcea/examples/chk_cea_addpropellant_user.py
rocketcea/examples/chk_cea_debug.py
rocketcea/examples/chk_cea_long_name.py
rocketcea/examples/chk_cea_temp_workingdir.py
rocketcea-1.2.2.dist-info/RECORD
