Metadata-Version: 2.1
Name: rocketcea
Version: 1.2.2
Project-URL: Documentation, http://rocketcea.readthedocs.org/en/latest/
Project-URL: Repository, https://github.com/sonofeft/RocketCEA
Project-URL: Bug Tracker, https://github.com/sonofeft/RocketCEA/issues
Requires-Dist: numpy
Requires-Dist: scipy
Requires-Dist: matplotlib
Provides-Extra: dev
Requires-Dist: check-manifest; extra == "dev"
Provides-Extra: test
Requires-Dist: pytest; extra == "test"
Requires-Dist: coverage; extra == "test"
Requires-Dist: nose; extra == "test"
